aiida_skeaf/__init__.py
aiida_skeaf/cli.py
aiida_skeaf/helpers.py
aiida_skeaf/calculations/__init__.py
aiida_skeaf/calculations/skeaf.py
aiida_skeaf/calculations/wan2skeaf.py
aiida_skeaf/calculations/functions/__init__.py
aiida_skeaf/data/__init__.py
aiida_skeaf/parsers/__init__.py
aiida_skeaf/parsers/skeaf.py
aiida_skeaf/parsers/wan2skeaf.py
aiida_skeaf/utils/__init__.py
aiida_skeaf/utils/builder.py
aiida_skeaf/utils/plot.py
aiida_skeaf/utils/str.py
aiida_skeaf/workflows/__init__.py
aiida_skeaf/workflows/protocols/__init__.py
aiida_skeaf/workflows/protocols/skeaf.yaml
aiida_skeaf-0.1.0.dist-info/entry_points.txt
aiida_skeaf-0.1.0.dist-info/licenses/LICENSE
aiida_skeaf-0.1.0.dist-info/WHEEL
aiida_skeaf-0.1.0.dist-info/METADATA
aiida_skeaf-0.1.0.dist-info/RECORD
