Metadata-Version: 2.4
Name: aiida-skeaf
Version: 0.1.0
Summary: AiiDA plugin for the Supercell K-space Extremal Area Finder (SKEAF) code
Keywords: aiida,plugin
Author-email: Junfeng Qiao <qiaojunfeng@outlook.com>
Requires-Python: >=3.7
Classifier: Programming Language :: Python
Classifier: Intended Audience :: Science/Research
Classifier: License :: OSI Approved :: MIT License
Classifier: Natural Language :: English
Classifier: Development Status :: 3 - Alpha
Classifier: Framework :: AiiDA
License-File: LICENSE
Requires-Dist: aiida-core>=1.6.4,<3
Requires-Dist: aiida-wannier90-workflows>=2.1.0
Requires-Dist: voluptuous
Requires-Dist: matplotlib ; extra == "analysis"
Requires-Dist: sphinx ; extra == "docs"
Requires-Dist: sphinxcontrib-contentui ; extra == "docs"
Requires-Dist: sphinxcontrib-details-directive ; extra == "docs"
Requires-Dist: furo ; extra == "docs"
Requires-Dist: markupsafe<2.1 ; extra == "docs"
Requires-Dist: pre-commit~=2.2 ; extra == "pre-commit"
Requires-Dist: pylint>=2.5.0,<2.9 ; extra == "pre-commit"
Requires-Dist: pgtest~=1.3.1 ; extra == "testing"
Requires-Dist: wheel~=0.31 ; extra == "testing"
Requires-Dist: coverage[toml] ; extra == "testing"
Requires-Dist: pytest~=6.0 ; extra == "testing"
Requires-Dist: pytest-cov ; extra == "testing"
Requires-Dist: pytest-regressions ; extra == "testing"
Project-URL: Source, https://github.com/aiidaplugins/aiida-skeaf
Provides-Extra: analysis
Provides-Extra: docs
Provides-Extra: pre-commit
Provides-Extra: testing
